.gitignore
LICENSE
MANIFEST.in
README.rst
requirements.txt
setup.cfg
setup.py
versioneer.py
jsonpath_flatten/__init__.py
jsonpath_flatten/_version.py
jsonpath_flatten.egg-info/PKG-INFO
jsonpath_flatten.egg-info/SOURCES.txt
jsonpath_flatten.egg-info/dependency_links.txt
jsonpath_flatten.egg-info/entry_points.txt
jsonpath_flatten.egg-info/not-zip-safe
jsonpath_flatten.egg-info/pbr.json
jsonpath_flatten.egg-info/requires.txt
jsonpath_flatten.egg-info/top_level.txt
tests/__init__.py
tests/jsonpath_flatten_test.py