Metadata-Version: 1.1
Name: jsonpath-flatten
Version: 0.1.post5
Summary: Flatten a dictionary into a single layer with JSONPath keys
Home-page: https://github.com/clearclaw/jsonpath_flatten
Author: J C Lawrence
Author-email: claw@kanga.nu
License: LGPL v3
Keywords: celery event logger
Platform: UNKNOWN
Classifier: Development Status :: 4 - Beta
Classifier: Intended Audience :: Developers
Classifier: License :: OSI Approved :: GNU Lesser General Public License v3 or later (LGPLv3+)
Classifier: Topic :: Utilities
